neo4j_viz/__init__.py
neo4j_viz/colors.py
neo4j_viz/gds.py
neo4j_viz/gql_create.py
neo4j_viz/neo4j.py
neo4j_viz/node.py
neo4j_viz/node_size.py
neo4j_viz/nvl.py
neo4j_viz/options.py
neo4j_viz/pandas.py
neo4j_viz/py.typed
neo4j_viz/relationship.py
neo4j_viz/snowflake.py
neo4j_viz/visualization_graph.py
neo4j_viz/resources/__init__.py
neo4j_viz/resources/icons/__init__.py
neo4j_viz/resources/icons/screenshot.svg
neo4j_viz/resources/icons/zoom-in.svg
neo4j_viz/resources/icons/zoom-out.svg
neo4j_viz/resources/nvl_entrypoint/__init__.py
neo4j_viz/resources/nvl_entrypoint/base.js
neo4j_viz/resources/nvl_entrypoint/styles.css
neo4j_viz-1.0.0.dist-info/licenses/LICENSE
neo4j_viz-1.0.0.dist-info/METADATA
neo4j_viz-1.0.0.dist-info/WHEEL
neo4j_viz-1.0.0.dist-info/top_level.txt
neo4j_viz-1.0.0.dist-info/RECORD
