Metadata-Version: 2.4
Name: neo4j-viz
Version: 1.0.0
Summary: A simple graph visualization tool
Author-email: Neo4j <team-gds@neo4j.org>
License-Expression: GPL-3.0-only
Project-URL: Homepage, https://neo4j.com/
Project-URL: Repository, https://github.com/neo4j/python-graph-visualization
Project-URL: Issues, https://github.com/neo4j/python-graph-visualization/issues
Project-URL: Documentation, https://neo4j.com/docs/python-graph-visualization/
Keywords: graph,visualization,neo4j
Classifier: Development Status :: 5 - Production/Stable
Classifier: Intended Audience :: Developers
Classifier: Intended Audience :: Science/Research
Classifier: Operating System :: OS Independent
Classifier: Programming Language :: Python
Classifier: Programming Language :: Python :: 3
Classifier: Programming Language :: Python :: 3 :: Only
Classifier: Programming Language :: Python :: 3.10
Classifier: Programming Language :: Python :: 3.11
Classifier: Programming Language :: Python :: 3.12
Classifier: Programming Language :: Python :: 3.13
Classifier: Topic :: Database :: Front-Ends
Classifier: Topic :: Scientific/Engineering
Classifier: Topic :: Scientific/Engineering :: Visualization
Classifier: Topic :: Software Development
Classifier: Typing :: Typed
Requires-Python: >=3.10
License-File: LICENSE
Requires-Dist: ipython<10,>=7
Requires-Dist: pydantic<3,>=2
Requires-Dist: pydantic-extra-types<3,>=2
Requires-Dist: enum-tools==0.13.0
Provides-Extra: dev
Requires-Dist: ruff==0.14.1; extra == "dev"
Requires-Dist: mypy==1.18.2; extra == "dev"
Requires-Dist: pytest==8.4.2; extra == "dev"
Requires-Dist: selenium==4.32.0; extra == "dev"
Requires-Dist: ipykernel==6.30.1; extra == "dev"
Requires-Dist: palettable==3.3.3; extra == "dev"
Requires-Dist: pytest-mock==3.14.0; extra == "dev"
Requires-Dist: nbconvert==7.16.6; extra == "dev"
Requires-Dist: streamlit==1.45.0; extra == "dev"
Requires-Dist: matplotlib>=3.9.4; extra == "dev"
Provides-Extra: docs
Requires-Dist: sphinx==8.1.3; extra == "docs"
Requires-Dist: enum-tools[sphinx]; extra == "docs"
Requires-Dist: nbsphinx==0.9.7; extra == "docs"
Requires-Dist: nbsphinx-link==1.3.1; extra == "docs"
Provides-Extra: pandas
Requires-Dist: pandas<3,>=2; extra == "pandas"
Requires-Dist: pandas-stubs<3,>=2; extra == "pandas"
Provides-Extra: gds
Requires-Dist: graphdatascience<2,>=1; extra == "gds"
Provides-Extra: neo4j
Requires-Dist: neo4j; extra == "neo4j"
Provides-Extra: snowflake
Requires-Dist: snowflake-snowpark-python<2,>=1; extra == "snowflake"
Provides-Extra: notebook
Requires-Dist: ipykernel>=6.29.5; extra == "notebook"
Requires-Dist: pykernel>=0.1.6; extra == "notebook"
Requires-Dist: neo4j>=5.26.0; extra == "notebook"
Requires-Dist: ipywidgets>=8.0.0; extra == "notebook"
Requires-Dist: palettable>=3.3.3; extra == "notebook"
Requires-Dist: matplotlib>=3.9.4; extra == "notebook"
Requires-Dist: snowflake-snowpark-python==1.37.0; extra == "notebook"
Dynamic: license-file
